Metadata-Version: 1.1
Name: sulley
Version: 0.1.0b0
Summary: With Sulley, you can build SMS bots in just a few lines of code. Powered by Twilio & Plivo, Sulley requires very minimal configuration and code to bring your bot to life!
Home-page: https://github.com/sandeepraju/sulley
Author: Sandeep Raju Prabhakar
Author-email: me@sandeepraju.in
License: BSD 3-Clause License
